jase/__init__.py
jase/jase.py
jase/data/dict_v1.csv
jase/data/edgar_10k_2010_100.csv
jase-0.1.5.dist-info/DESCRIPTION.rst
jase-0.1.5.dist-info/METADATA
jase-0.1.5.dist-info/RECORD
jase-0.1.5.dist-info/WHEEL
jase-0.1.5.dist-info/metadata.json
jase-0.1.5.dist-info/top_level.txt
