Metadata-Version: 2.0
Name: jase
Version: 0.1.5
Summary: Just A Simple Sentiment Analysis Tool for English
Home-page: UNKNOWN
Author: Hsin-Min Lu
Author-email: luim@ntu.edu.tw
License: UNKNOWN
Keywords: sentiment_analysis English
Platform: UNKNOWN
Classifier: Development Status :: 3 - Alpha
Classifier: Intended Audience :: Science/Research
Classifier: Topic :: Scientific/Engineering :: Artificial Intelligence
Classifier: License :: OSI Approved :: GNU General Public License v3 or later (GPLv3+)
Classifier: Programming Language :: Python :: 3
Classifier: Programming Language :: Python :: 3.4
Classifier: Programming Language :: Python :: 3.5
Classifier: Programming Language :: Python :: 3.6
Classifier: Programming Language :: Python :: 3.7
Requires-Dist: pandas
